gym_notices/__init__.py
gym_notices/notices.py
gym_notices-0.0.3.dist-info/LICENSE.txt
gym_notices-0.0.3.dist-info/METADATA
gym_notices-0.0.3.dist-info/WHEEL
gym_notices-0.0.3.dist-info/top_level.txt
gym_notices-0.0.3.dist-info/RECORD
