Metadata-Version: 2.1
Name: gym-notices
Version: 0.0.3
Summary: Notices for gym
Home-page: https://github.com/Farama-Foundation/gym-notices
Author: Jordan Terry
Author-email: jkterry@umd.edu
License: UNKNOWN
Platform: UNKNOWN
Classifier: Programming Language :: Python :: 3
Classifier: License :: OSI Approved :: MIT License
Classifier: Operating System :: OS Independent
License-File: LICENSE.txt
